[
    {
        "url": "iv.ggtyler.dev",
        "latency": 0.3697240352630615
    },
    {
        "url": "invidious.privacyredirect.com",
        "latency": 0.4181230068206787
    },
    {
        "url": "invidious.reallyaweso.me",
        "latency": 0.42455053329467773
    },
    {
        "url": "iv.nboeck.de",
        "latency": 0.4581923484802246
    },
    {
        "url": "invidious.yourdevice.ch",
        "latency": 0.4886283874511719
    },
    {
        "url": "iv.nowhere.moe",
        "latency": 0.5283713340759277
    },
    {
        "url": "inv.nadeko.net",
        "latency": 0.546912670135498
    },
    {
        "url": "yewtu.be",
        "latency": 0.6686158180236816
    },
    {
        "url": "inv.tux.pizza",
        "latency": 0.7530326843261719
    },
    {
        "url": "invidious.adminforge.de",
        "latency": 0.8222095966339111
    },
    {
        "url": "invidious.privacydev.net",
        "latency": 0.8915996551513672
    }
]