[
    {
        "url": "invidious.privacyredirect.com",
        "latency": 0.4067881107330322
    },
    {
        "url": "invidious.reallyaweso.me",
        "latency": 0.434018611907959
    },
    {
        "url": "inv.tux.pizza",
        "latency": 0.4470961093902588
    },
    {
        "url": "yewtu.be",
        "latency": 0.5011348724365234
    },
    {
        "url": "iv.nboeck.de",
        "latency": 0.529041051864624
    },
    {
        "url": "iv.nowhere.moe",
        "latency": 0.5443892478942871
    },
    {
        "url": "invidious.yourdevice.ch",
        "latency": 0.673736572265625
    },
    {
        "url": "inv.nadeko.net",
        "latency": 0.8247931003570557
    },
    {
        "url": "invidious.jing.rocks",
        "latency": 0.8725533485412598
    },
    {
        "url": "invidious.adminforge.de",
        "latency": 1.0083200931549072
    },
    {
        "url": "invidious.privacydev.net",
        "latency": 1.348536729812622
    }
]