[
    {
        "url": "iv.ggtyler.dev",
        "latency": 0.4531705379486084
    },
    {
        "url": "yewtu.be",
        "latency": 0.4590597152709961
    },
    {
        "url": "invidious.reallyaweso.me",
        "latency": 0.5414488315582275
    },
    {
        "url": "inv.tux.pizza",
        "latency": 0.5718321800231934
    },
    {
        "url": "invidious.yourdevice.ch",
        "latency": 0.5784471035003662
    },
    {
        "url": "iv.nboeck.de",
        "latency": 0.5796301364898682
    },
    {
        "url": "inv.nadeko.net",
        "latency": 0.6068356037139893
    },
    {
        "url": "iv.nowhere.moe",
        "latency": 0.7025494575500488
    },
    {
        "url": "invidious.privacydev.net",
        "latency": 0.7772371768951416
    },
    {
        "url": "invidious.adminforge.de",
        "latency": 0.9398350715637207
    },
    {
        "url": "invidious.jing.rocks",
        "latency": 1.0042595863342285
    },
    {
        "url": "invidious.privacyredirect.com",
        "latency": 1.0807971954345703
    }
]