[
    {
        "url": "yewtu.be",
        "latency": 0.402937650680542
    },
    {
        "url": "invidious.privacyredirect.com",
        "latency": 0.5170233249664307
    },
    {
        "url": "iv.nboeck.de",
        "latency": 0.5803284645080566
    },
    {
        "url": "iv.nowhere.moe",
        "latency": 0.6293110847473145
    },
    {
        "url": "invidious.reallyaweso.me",
        "latency": 0.6580660343170166
    },
    {
        "url": "invidious.yourdevice.ch",
        "latency": 0.6732113361358643
    },
    {
        "url": "iv.ggtyler.dev",
        "latency": 0.7843952178955078
    },
    {
        "url": "invidious.adminforge.de",
        "latency": 0.8182048797607422
    },
    {
        "url": "invidious.jing.rocks",
        "latency": 0.8788223266601562
    },
    {
        "url": "inv.tux.pizza",
        "latency": 0.9704771041870117
    },
    {
        "url": "inv.nadeko.net",
        "latency": 1.6381385326385498
    },
    {
        "url": "invidious.privacydev.net",
        "latency": 1.7141907215118408
    }
]