[
    {
        "url": "iv.ggtyler.dev",
        "latency": 0.2629396915435791
    },
    {
        "url": "invidious.privacyredirect.com",
        "latency": 0.4463686943054199
    },
    {
        "url": "inv.tux.pizza",
        "latency": 0.44950389862060547
    },
    {
        "url": "yewtu.be",
        "latency": 0.4888129234313965
    },
    {
        "url": "invidious.privacydev.net",
        "latency": 0.6200418472290039
    },
    {
        "url": "invidious.yourdevice.ch",
        "latency": 0.6253447532653809
    },
    {
        "url": "iv.nowhere.moe",
        "latency": 0.6285178661346436
    },
    {
        "url": "invidious.reallyaweso.me",
        "latency": 0.6578421592712402
    },
    {
        "url": "invidious.adminforge.de",
        "latency": 0.6787364482879639
    },
    {
        "url": "iv.nboeck.de",
        "latency": 0.7012581825256348
    }
]