[
    {
        "url": "yewtu.be",
        "latency": 0.6960945129394531
    },
    {
        "url": "inv.tux.pizza",
        "latency": 0.7250914573669434
    },
    {
        "url": "invidious.reallyaweso.me",
        "latency": 0.802739143371582
    },
    {
        "url": "invidious.adminforge.de",
        "latency": 0.8155407905578613
    },
    {
        "url": "invidious.yourdevice.ch",
        "latency": 0.8322491645812988
    },
    {
        "url": "inv.nadeko.net",
        "latency": 0.8464999198913574
    },
    {
        "url": "iv.ggtyler.dev",
        "latency": 0.8609428405761719
    },
    {
        "url": "iv.nboeck.de",
        "latency": 0.9039466381072998
    },
    {
        "url": "iv.nowhere.moe",
        "latency": 1.157607078552246
    },
    {
        "url": "invidious.privacydev.net",
        "latency": 1.5195386409759521
    },
    {
        "url": "invidious.privacyredirect.com",
        "latency": 2.7025623321533203
    }
]