[
    {
        "url": "inv.tux.pizza",
        "latency": 0.5828731060028076
    },
    {
        "url": "invidious.reallyaweso.me",
        "latency": 0.6460096836090088
    },
    {
        "url": "yewtu.be",
        "latency": 0.6537232398986816
    },
    {
        "url": "invidious.jing.rocks",
        "latency": 0.7418332099914551
    },
    {
        "url": "inv.nadeko.net",
        "latency": 0.7691168785095215
    },
    {
        "url": "invidious.yourdevice.ch",
        "latency": 0.8163363933563232
    },
    {
        "url": "iv.ggtyler.dev",
        "latency": 0.8338956832885742
    },
    {
        "url": "invidious.adminforge.de",
        "latency": 0.8393032550811768
    },
    {
        "url": "iv.nboeck.de",
        "latency": 0.9187531471252441
    },
    {
        "url": "iv.nowhere.moe",
        "latency": 1.2476425170898438
    },
    {
        "url": "invidious.privacyredirect.com",
        "latency": 1.2810473442077637
    },
    {
        "url": "invidious.privacydev.net",
        "latency": 1.566434383392334
    }
]