[
    {
        "url": "invidious.privacyredirect.com",
        "latency": 0.6996374130249023
    },
    {
        "url": "iv.ggtyler.dev",
        "latency": 0.70513916015625
    },
    {
        "url": "invidious.reallyaweso.me",
        "latency": 0.7140035629272461
    },
    {
        "url": "inv.tux.pizza",
        "latency": 0.7867295742034912
    },
    {
        "url": "yewtu.be",
        "latency": 0.796032190322876
    },
    {
        "url": "iv.nboeck.de",
        "latency": 1.056535005569458
    },
    {
        "url": "inv.nadeko.net",
        "latency": 1.339353322982788
    },
    {
        "url": "invidious.adminforge.de",
        "latency": 1.7880301475524902
    },
    {
        "url": "iv.nowhere.moe",
        "latency": 2.3004238605499268
    },
    {
        "url": "invidious.jing.rocks",
        "latency": 2.4577062129974365
    }
]