[
    {
        "url": "iv.ggtyler.dev",
        "latency": 0.10531020164489746
    },
    {
        "url": "inv.tux.pizza",
        "latency": 0.2851424217224121
    },
    {
        "url": "invidious.yourdevice.ch",
        "latency": 0.36866235733032227
    },
    {
        "url": "yewtu.be",
        "latency": 0.4173455238342285
    },
    {
        "url": "invidious.reallyaweso.me",
        "latency": 0.4376647472381592
    },
    {
        "url": "invidious.privacyredirect.com",
        "latency": 0.6930627822875977
    }
]